tcl_toolkit-0.510.data/data/tentacle/slots/maya/utils_maya/shader_utils_maya/stingray_arnold_shader.ui
tcl_toolkit-0.510.data/data/tentacle/ui/0/init.ui
tcl_toolkit-0.510.data/data/tentacle/ui/1/cameras.ui
tcl_toolkit-0.510.data/data/tentacle/ui/1/editors.ui
tcl_toolkit-0.510.data/data/tentacle/ui/1/main.ui
tcl_toolkit-0.510.data/data/tentacle/ui/2/animation_submenu.ui
tcl_toolkit-0.510.data/data/tentacle/ui/2/cameras_lower_submenu.ui
tcl_toolkit-0.510.data/data/tentacle/ui/2/convert_submenu.ui
tcl_toolkit-0.510.data/data/tentacle/ui/2/crease_submenu.ui
tcl_toolkit-0.510.data/data/tentacle/ui/2/create_submenu.ui
tcl_toolkit-0.510.data/data/tentacle/ui/2/deformation_submenu.ui
tcl_toolkit-0.510.data/data/tentacle/ui/2/display_submenu.ui
tcl_toolkit-0.510.data/data/tentacle/ui/2/duplicate_submenu.ui
tcl_toolkit-0.510.data/data/tentacle/ui/2/edit_submenu.ui
tcl_toolkit-0.510.data/data/tentacle/ui/2/editors_lower_submenu.ui
tcl_toolkit-0.510.data/data/tentacle/ui/2/file_submenu.ui
tcl_toolkit-0.510.data/data/tentacle/ui/2/lighting_submenu.ui
tcl_toolkit-0.510.data/data/tentacle/ui/2/main_lower_submenu.ui
tcl_toolkit-0.510.data/data/tentacle/ui/2/materials_submenu.ui
tcl_toolkit-0.510.data/data/tentacle/ui/2/mirror_submenu.ui
tcl_toolkit-0.510.data/data/tentacle/ui/2/normals_submenu.ui
tcl_toolkit-0.510.data/data/tentacle/ui/2/nurbs_submenu.ui
tcl_toolkit-0.510.data/data/tentacle/ui/2/pivot_submenu.ui
tcl_toolkit-0.510.data/data/tentacle/ui/2/polygons_submenu#component.ui
tcl_toolkit-0.510.data/data/tentacle/ui/2/polygons_submenu#edge.ui
tcl_toolkit-0.510.data/data/tentacle/ui/2/polygons_submenu#face.ui
tcl_toolkit-0.510.data/data/tentacle/ui/2/polygons_submenu#mesh.ui
tcl_toolkit-0.510.data/data/tentacle/ui/2/polygons_submenu#vertex.ui
tcl_toolkit-0.510.data/data/tentacle/ui/2/polygons_submenu.ui
tcl_toolkit-0.510.data/data/tentacle/ui/2/preferences_submenu.ui
tcl_toolkit-0.510.data/data/tentacle/ui/2/rendering_submenu.ui
tcl_toolkit-0.510.dist-info/METADATA
tcl_toolkit-0.510.dist-info/WHEEL
tcl_toolkit-0.510.dist-info/top_level.txt
tcl_toolkit-0.510.dist-info/RECORD
