Metadata-Version: 2.1
Name: tcl-toolkit
Version: 0.510
Summary: A Python3/PySide2 marking menu style toolkit for Maya, 3ds Max, and Blender.
Home-page: https://github.com/m3trik/tentacle
Author: Ryan Simpson
Author-email: m3trik@outlook.com
Classifier: Programming Language :: Python :: 3
Classifier: Operating System :: OS Independent
